apidag/__init__.py
apidag/exceptions.py
apidag/executor.py
apidag/graph.py
apidag/node.py
apidag/nodes/__init__.py
apidag/nodes/http.py
apidag/nodes/source.py
apidag/nodes/transformer.py
apidag-0.2.2.dist-info/LICENSE
apidag-0.2.2.dist-info/METADATA
apidag-0.2.2.dist-info/WHEEL
apidag-0.2.2.dist-info/top_level.txt
apidag-0.2.2.dist-info/RECORD
