Metadata-Version: 2.2
Name: apidag
Version: 0.2.2
Summary: A Python library using asyncio and aiohttp to build declarative API call flows
Author-email: Sarahhhh <sarahhhhfoster@gmail.com>
Project-URL: Homepage, https://github.com/SarahhhhFoster/apidag
Project-URL: Bug Tracker, https://github.com/SarahhhhFoster/apidag/issues
Classifier: Programming Language :: Python :: 3
Classifier: License :: Other/Proprietary License
Classifier: Operating System :: OS Independent
Requires-Python: >=3.7
License-File: LICENSE
Requires-Dist: aiohttp<4,>=3.8.0
Requires-Dist: jsonpath-ng<2,>=1.5.0
Requires-Dist: typing-extensions>=4.0.0
Requires-Dist: asyncio>=3.4.3
Requires-Dist: networkx>=3.4.2
